riemapp/__init__.py
riemapp/core.py
riemapp/geometry.py
riemapp/py.typed
riemapp/version.py
riemapp/version.pyi
riemapp-0.2.0.dist-info/METADATA
riemapp-0.2.0.dist-info/WHEEL
riemapp-0.2.0.dist-info/licenses/LICENSE
riemapp-0.2.0.dist-info/RECORD
