Metadata-Version: 2.1
Name: riemapp
Version: 0.2.0
Summary: Manim powered complex mappings.
Project-URL: Bug Tracker, https://github.com/Saransh-cpp/riemapp/issues
Project-URL: Changelog, https://riemapp.readthedocs.io/en/latest/changelog/
Project-URL: Discussions, https://github.com/Saransh-cpp/riemapp/discussions
Project-URL: Documentation, https://riemapp.readthedocs.io/
Project-URL: Homepage, https://github.com/Saransh-cpp/riemapp
Author-email: Saransh Chopra <saransh0701@gmail.com>, Agriya Khetarpal <agriyakhetarpal@gmail.com>, Naman Priyadarshi <namanpriyadarshicr7@gmail.com>, Onkar Mahapatra <onkarmahapatra627@gmail.com>, Parth Tripathi <parthxtripathi03@gmail.com>
License-File: LICENSE
Classifier: Development Status :: 4 - Beta
Classifier: Intended Audience :: Developers
Classifier: Intended Audience :: Science/Research
Classifier: License :: OSI Approved :: MIT License
Classifier: Operating System :: OS Independent
Classifier: Programming Language :: Python
Classifier: Programming Language :: Python :: 3 :: Only
Classifier: Programming Language :: Python :: 3.7
Classifier: Programming Language :: Python :: 3.8
Classifier: Programming Language :: Python :: 3.9
Classifier: Programming Language :: Python :: 3.10
Classifier: Programming Language :: Python :: 3.11
Classifier: Topic :: Scientific/Engineering
Classifier: Typing :: Typed
Requires-Python: >=3.7
Requires-Dist: manim>=0.16
Provides-Extra: dev
Requires-Dist: pytest-cov>=3; extra == 'dev'
Requires-Dist: pytest>=6; extra == 'dev'
Provides-Extra: docs
Requires-Dist: markdown-callouts>=0.2; extra == 'docs'
Requires-Dist: mkdocs-include-exclude-files>=0.0.1; extra == 'docs'
Requires-Dist: mkdocs-jupyter>=0.21; extra == 'docs'
Requires-Dist: mkdocs-material>=8.3.9; extra == 'docs'
Requires-Dist: mkdocs>=1.3.1; extra == 'docs'
Requires-Dist: mkdocstrings-python-legacy>=0.2.3; extra == 'docs'
Requires-Dist: mkdocstrings-python>=0.7.1; extra == 'docs'
Requires-Dist: pymdown-extensions>=9.5; extra == 'docs'
Provides-Extra: test
Requires-Dist: pytest-cov>=3; extra == 'test'
Requires-Dist: pytest>=6; extra == 'test'
